odoo9_addon_stock_inventory_revaluation-9.0.1.0.0-py2.7-nspkg.pth
odoo_addons/stock_inventory_revaluation/__openerp__.py
odoo_addons/stock_inventory_revaluation/__init__.py
odoo_addons/stock_inventory_revaluation/README.rst
odoo_addons/stock_inventory_revaluation/security/stock_inventory_revaluation_security.xml
odoo_addons/stock_inventory_revaluation/security/ir.model.access.csv
odoo_addons/stock_inventory_revaluation/migrations/9.0.1.0.0/pre-migration.py
odoo_addons/stock_inventory_revaluation/migrations/9.0.1.0.0/openupgrade_analysis_work.txt
odoo_addons/stock_inventory_revaluation/migrations/9.0.1.0.0/openupgrade_analysis.txt
odoo_addons/stock_inventory_revaluation/migrations/9.0.1.0.0/post-migration.py
odoo_addons/stock_inventory_revaluation/models/product.py
odoo_addons/stock_inventory_revaluation/models/stock_inventory_revaluation.py
odoo_addons/stock_inventory_revaluation/models/__init__.py
odoo_addons/stock_inventory_revaluation/models/account_move.py
odoo_addons/stock_inventory_revaluation/views/account_move_line_view.xml
odoo_addons/stock_inventory_revaluation/views/product_view.xml
odoo_addons/stock_inventory_revaluation/views/stock_inventory_revaluation_view.xml
odoo_addons/stock_inventory_revaluation/wizards/stock_inventory_revaluation_mass_post_view.xml
odoo_addons/stock_inventory_revaluation/wizards/stock_inventory_revaluation_mass_post.py
odoo_addons/stock_inventory_revaluation/wizards/__init__.py
odoo_addons/stock_inventory_revaluation/wizards/stock_inventory_revaluation_get_quants.py
odoo_addons/stock_inventory_revaluation/wizards/stock_inventory_revaluation_get_quants_view.xml
odoo_addons/stock_inventory_revaluation/data/stock_inventory_revaluation_data.xml
odoo_addons/stock_inventory_revaluation/tests/test_stock_inventory_revaluation.py
odoo_addons/stock_inventory_revaluation/tests/__init__.py
odoo_addons/stock_inventory_revaluation/static/description/icon.png
odoo9_addon_stock_inventory_revaluation-9.0.1.0.0.dist-info/top_level.txt
odoo9_addon_stock_inventory_revaluation-9.0.1.0.0.dist-info/WHEEL
odoo9_addon_stock_inventory_revaluation-9.0.1.0.0.dist-info/RECORD
odoo9_addon_stock_inventory_revaluation-9.0.1.0.0.dist-info/metadata.json
odoo9_addon_stock_inventory_revaluation-9.0.1.0.0.dist-info/DESCRIPTION.rst
odoo9_addon_stock_inventory_revaluation-9.0.1.0.0.dist-info/METADATA
odoo9_addon_stock_inventory_revaluation-9.0.1.0.0.dist-info/namespace_packages.txt
